better-mlm-scoring/.git/FETCH_HEAD
better-mlm-scoring/.git/HEAD
better-mlm-scoring/.git/ORIG_HEAD
better-mlm-scoring/.git/config
better-mlm-scoring/.git/description
better-mlm-scoring/.git/hooks/applypatch-msg.sample
better-mlm-scoring/.git/hooks/commit-msg.sample
better-mlm-scoring/.git/hooks/fsmonitor-watchman.sample
better-mlm-scoring/.git/hooks/post-update.sample
better-mlm-scoring/.git/hooks/pre-applypatch.sample
better-mlm-scoring/.git/hooks/pre-commit.sample
better-mlm-scoring/.git/hooks/pre-merge-commit.sample
better-mlm-scoring/.git/hooks/pre-push.sample
better-mlm-scoring/.git/hooks/pre-rebase.sample
better-mlm-scoring/.git/hooks/pre-receive.sample
better-mlm-scoring/.git/hooks/prepare-commit-msg.sample
better-mlm-scoring/.git/hooks/update.sample
better-mlm-scoring/.git/index
better-mlm-scoring/.git/info/exclude
better-mlm-scoring/.git/logs/HEAD
better-mlm-scoring/.git/logs/refs/heads/master
better-mlm-scoring/.git/logs/refs/heads/pr-branch-into-minicons
better-mlm-scoring/.git/logs/refs/remotes/origin/HEAD
better-mlm-scoring/.git/logs/refs/remotes/origin/master
better-mlm-scoring/.git/logs/refs/stash
better-mlm-scoring/.git/objects/38/32c567e61f4b4bef6fea03164afbed59dd703b
better-mlm-scoring/.git/objects/47/23e73222d3f3f2460bccf7eb3c4d6b17202998
better-mlm-scoring/.git/objects/52/09f6286b23363127a019d1fceef131699e98d4
better-mlm-scoring/.git/objects/61/1cfbd062437f1ff9bb78862ea07be0f05bc398
better-mlm-scoring/.git/objects/6e/2915ffb1606af9aae4712d48a960fab3c1644e
better-mlm-scoring/.git/objects/a9/a3015d5205460d28fa3bc56bb096458edb417a
better-mlm-scoring/.git/objects/af/597c2a78319f47de849ecf5d8c38eb282f3a94
better-mlm-scoring/.git/objects/pack/pack-cb508fd9c5784e65ecb4c3b188d3594f92264dc0.idx
better-mlm-scoring/.git/objects/pack/pack-cb508fd9c5784e65ecb4c3b188d3594f92264dc0.pack
better-mlm-scoring/.git/packed-refs
better-mlm-scoring/.git/refs/heads/master
better-mlm-scoring/.git/refs/heads/pr-branch-into-minicons
surprisal-0.1.7.dist-info/METADATA
surprisal-0.1.7.dist-info/WHEEL
surprisal-0.1.7.dist-info/entry_points.txt
surprisal-0.1.7.dist-info/licenses/LICENSE
surprisal-0.1.7.dist-info/RECORD
