Metadata-Version: 2.1
Name: surprisal
Version: 0.1.7
Summary: A package to conveniently compute surprisals for text sequences and subsequences
Author-Email: aalok-sathe <asathe@mit.edu>
License: MIT
Project-URL: homepage, https://github.com/aalok-sathe/surprisal
Project-URL: repository, https://github.com/aalok-sathe/surprisal
Requires-Python: <4.0,>=3.9
Requires-Dist: numpy>=1.23.1
Requires-Dist: plotext<6.0.0,>=5.0.2
Requires-Dist: matplotlib>=3.5.2
Provides-Extra: transformers
Requires-Dist: huggingface-hub>=0; extra == "transformers"
Requires-Dist: torch>=2.6; extra == "transformers"
Requires-Dist: transformers>=4.43.0; extra == "transformers"
Provides-Extra: kenlm
Requires-Dist: kenlm>=0.3.0; extra == "kenlm"
Provides-Extra: petals
Requires-Dist: petals>=2.2.0; extra == "petals"
Provides-Extra: all
Requires-Dist: kenlm>=0.3.0; extra == "all"
Requires-Dist: torch>=2.5.1; extra == "all"
Requires-Dist: transformers>=4.34.1; extra == "all"
Requires-Dist: petals>=2.2.0; extra == "all"
